setup.py
dist_energy/Binomialdistribution.py
dist_energy/Gaussiandistribution.py
dist_energy/Generaldistribution.py
dist_energy/__init__.py
dist_energy.egg-info/PKG-INFO
dist_energy.egg-info/SOURCES.txt
dist_energy.egg-info/dependency_links.txt
dist_energy.egg-info/not-zip-safe
dist_energy.egg-info/top_level.txt